asdf_inspect/__init__.py
asdf_inspect/exceptions.py
asdf_inspect/inspect.py
asdf_inspect/path.py
asdf_inspect/spec.py
asdf_inspect/version.py
asdf_inspect-0.1.0.dist-info/LICENSE
asdf_inspect-0.1.0.dist-info/WHEEL
asdf_inspect-0.1.0.dist-info/METADATA
asdf_inspect-0.1.0.dist-info/RECORD
